poetry_multiproject_plugin/__init__.py
poetry_multiproject_plugin/commands/__init__.py
poetry_multiproject_plugin/commands/buildproject/__init__.py
poetry_multiproject_plugin/commands/buildproject/project.py
poetry_multiproject_plugin/commands/checkproject/__init__.py
poetry_multiproject_plugin/commands/checkproject/check.py
poetry_multiproject_plugin/components/__init__.py
poetry_multiproject_plugin/components/check/__init__.py
poetry_multiproject_plugin/components/check/mypy_checker.py
poetry_multiproject_plugin/components/deps/__init__.py
poetry_multiproject_plugin/components/deps/installer.py
poetry_multiproject_plugin/components/parsing/__init__.py
poetry_multiproject_plugin/components/parsing/rewrite.py
poetry_multiproject_plugin/components/project/__init__.py
poetry_multiproject_plugin/components/project/cleanup.py
poetry_multiproject_plugin/components/project/copying.py
poetry_multiproject_plugin/components/project/create.py
poetry_multiproject_plugin/components/project/dist.py
poetry_multiproject_plugin/components/project/packages.py
poetry_multiproject_plugin/components/project/prepare.py
poetry_multiproject_plugin/components/toml/__init__.py
poetry_multiproject_plugin/components/toml/generate.py
poetry_multiproject_plugin/components/toml/packages.py
poetry_multiproject_plugin/components/toml/read.py
poetry_multiproject_plugin/plugin.py
poetry_multiproject_plugin-1.8.4.dist-info/LICENSE
poetry_multiproject_plugin-1.8.4.dist-info/METADATA
poetry_multiproject_plugin-1.8.4.dist-info/WHEEL
poetry_multiproject_plugin-1.8.4.dist-info/entry_points.txt
poetry_multiproject_plugin-1.8.4.dist-info/RECORD
