Metadata-Version: 2.3
Name: poetry-multiproject-plugin
Version: 1.8.4
Summary: A Poetry plugin that makes it possible to use relative package includes.
License: MIT
Author: David Vujic
Requires-Python: >=3.8,<4.0
Classifier: License :: OSI Approved :: MIT License
Classifier: Programming Language :: Python :: 3
Classifier: Programming Language :: Python :: 3.8
Classifier: Programming Language :: Python :: 3.9
Classifier: Programming Language :: Python :: 3.10
Classifier: Programming Language :: Python :: 3.11
Classifier: Programming Language :: Python :: 3.12
Classifier: Programming Language :: Python :: 3.13
Requires-Dist: mypy (==1.*)
Requires-Dist: poetry
Requires-Dist: tomlkit (==0.*)
Project-URL: Homepage, https://github.com/davidvujic/poetry-multiproject-plugin
Project-URL: Repository, https://github.com/davidvujic/poetry-multiproject-plugin
